bgu_physics_lab_b/__init__.py
bgu_physics_lab_b/regression.py
bgu_physics_lab_b-0.1.dist-info/LICENSE.txt
bgu_physics_lab_b-0.1.dist-info/METADATA
bgu_physics_lab_b-0.1.dist-info/WHEEL
bgu_physics_lab_b-0.1.dist-info/top_level.txt
bgu_physics_lab_b-0.1.dist-info/RECORD
