Metadata-Version: 2.1
Name: bgu-physics-lab-b
Version: 0.1
Summary: plot and caluclate fiting goodness using chi2 regression
Home-page: https://github.com/bguphysicslab/bgu_physics_lab_b
Author: Adam H. Agbaria
Author-email: adam.h.agb@gmail.com
License: MIT
Download-URL: https://github.com/bguphysicslab/bgu_physics_lab_b/releases/tag/0.1.tar.gz
Keywords: chi2,regression,physics_lab
Platform: UNKNOWN
Classifier: Development Status :: 3 - Alpha
Classifier: Intended Audience :: Developers
Classifier: Topic :: Software Development :: Build Tools
Classifier: License :: OSI Approved :: MIT License
Classifier: Programming Language :: Python :: 3
Classifier: Programming Language :: Python :: 3.4
Classifier: Programming Language :: Python :: 3.5
Classifier: Programming Language :: Python :: 3.6
Requires-Dist: matplotlib
Requires-Dist: iminuit
Requires-Dist: numpy
